{"inkVersion":18,"root":[["^I love this time of night.","\n","ev","str","^Why's that?","/str","/ev",{"*":"0.c-0","flg":20},"ev","str","^It is beautiful out","/str","/ev",{"*":"0.c-1","flg":20},"ev","str","^I think it's kinda creepy...","/str","/ev",{"*":"0.c-2","flg":20},{"c-0":["\n","^The crickets have just gone to sleep.","\n",{"->":"sit_down"},{"->":"0.g-0"},{"#f":7}],"c-1":["\n","^Yea","\n",{"->":"sit_down"},{"->":"0.g-0"},{"#f":7}],"c-2":["\n","^What exactly are you scared of?","\n",{"->":"sit_down"},{"->":"0.g-0"},{"#f":7}],"g-0":["done",{"#f":7}]}],"done",{"sit_down":["^You seem fresh.","\n","^Your beat's just begun, I take it.","\n","^And you feel bad for missing home already.","\n","end",{"#f":3}],"#f":3}],"listDefs":{}}